{
  "1":{
    "photo":"anusaya.jpg",
    "thumb":"anusaya_thumb.jpg",
    "name": "Anusaya Dhara",
    "caption":"The pious moment of lighting '108 diyas'.<br>The holy 'Shandhi Puja' of SharodUtsav<br>"
  },
  "2":{
    "photo":"deeksha.jpg",
    "thumb":"deeksha_thumb.jpg",
    "name": "Deeksha Sinha",
    "caption":"Sky above me, Earth below me , fire within me<br>"
  },
  "3":{
    "photo":"avishek.jpg",
    "thumb":"avishek_thumb.jpg",
    "name": "Avishek Dey",
    "caption":"<br>"
  },
  "4":{
    "photo":"sabyasachi.jpg",
    "thumb":"sabyasachi_thumb.jpg",
    "name": "Sabyasachi Moitra",
    "caption":"মাতৃ শক্তি<br>"
  },
  "5":{
    "photo":"sabyasachi1.jpg",
    "thumb":"sabyasachi1_thumb.jpg",
    "name": "Sabyasachi Moitra",
    "caption":"মসুনশান<br>"
  },
  "6":{
    "photo":"arindam.jpg",
    "thumb":"arindam_thumb.jpg",
    "name": "Arindam Ray",
    "caption":"<br>"
  }

}